katalytic-0.5.1.dist-info/METADATA
katalytic-0.5.1.dist-info/WHEEL
katalytic-0.5.1.dist-info/entry_points.txt
katalytic-0.5.1.dist-info/licenses/LICENSE.txt
katalytic/__init__.py
katalytic/_pkg.py
katalytic/data/__init__.py
katalytic/data/checks.py
katalytic/data/data.py
katalytic/files.py
katalytic/maths/__init__.py
katalytic/maths/bboxes.py
katalytic/maths/maths.py
katalytic/meta.py
katalytic-0.5.1.dist-info/RECORD
