Metadata-Version: 2.1
Name: katalytic
Version: 0.5.1
Summary: We'll take care of the boilerplate, so you can focus on your problems.
Keywords: automation,high-level,metaprogramming
Author-Email: Valentin Neagu <vali19th@protonmail.com>
License: Copyright 2023 - present, Valentin Neagu
Classifier: Development Status :: 3 - Alpha
Classifier: Intended Audience :: Developers
Classifier: Intended Audience :: System Administrators
Classifier: License :: OSI Approved :: MIT License
Classifier: Natural Language :: English
Classifier: Operating System :: OS Independent
Classifier: Programming Language :: Python :: 3
Classifier: Topic :: Software Development :: Libraries
Classifier: Topic :: System :: Filesystems
Classifier: Topic :: System :: Systems Administration
Classifier: Topic :: Text Processing
Classifier: Topic :: Utilities
Project-URL: Changelog, https://gitlab.com/katalytic/katalytic/-/blob/main/CHANGELOG.md
Project-URL: Homepage, https://gitlab.com/katalytic/katalytic.git
Project-URL: Repository, https://gitlab.com/katalytic/katalytic.git
Requires-Python: >=3.13
Provides-Extra: all
Requires-Dist: katalytic-images>=0.1.0; extra == "all"
Provides-Extra: dev
Requires-Dist: black; extra == "dev"
Requires-Dist: pre-commit; extra == "dev"
Requires-Dist: pytest; extra == "dev"
Requires-Dist: pytest-clarity; extra == "dev"
Requires-Dist: pytest-cov; extra == "dev"
Requires-Dist: pytest-randomly; extra == "dev"
Requires-Dist: pytest-repeat; extra == "dev"
Requires-Dist: pytest-xdist; extra == "dev"
